syncbyte/__init__.py
syncbyte/__main__.py
syncbyte/alembic.ini
syncbyte/config.py
syncbyte/constant.py
syncbyte/db.py
syncbyte/exceptions.py
syncbyte/main.py
syncbyte/scheduler.py
syncbyte/alembic/__init__.py
syncbyte/alembic/env.py
syncbyte/backup/__init__.py
syncbyte/backup/api.py
syncbyte/backup/local.py
syncbyte/backup/remote.py
syncbyte/celery/__init__.py
syncbyte/webapi/__init__.py
syncbyte/webapi/api.py
syncbyte/webapi/depends.py
syncbyte/webapi/controller/__init__.py
syncbyte/webapi/controller/controller.py
syncbyte/webapi/schema/__init__.py
syncbyte/webapi/schema/resource.py
syncbyte/webapi/schema/s3.py
syncbyte-0.1.0.dist-info/LICENSE
syncbyte-0.1.0.dist-info/METADATA
syncbyte-0.1.0.dist-info/WHEEL
syncbyte-0.1.0.dist-info/entry_points.txt
syncbyte-0.1.0.dist-info/top_level.txt
syncbyte-0.1.0.dist-info/RECORD
